{
    "Objects": [
        {
            "name": "Offroad_02",
            "pos": [
                4473.32958984375,
                340.1853942871094,
                10070.6875
            ],
            "ypr": [
                68.64898681640625,
                -1.3367584943771363,
                -1.7599586248397828
            ],
            "scale": 1.0,
            "enableCEPersistency": 0
        },
        {
            "name": "OffroadHatchback",
            "pos": [
                4471.49853515625,
                339.83404541015627,
                10077.427734375
            ],
            "ypr": [
                63.06471633911133,
                -1.8460419178009034,
                -1.3937674760818482
            ],
            "scale": 1.0,
            "enableCEPersistency": 0
        },
        {
            "name": "bldr_prop_CarRadiator",
            "pos": [
                4471.6611328125,
                339.46771240234377,
                10080.755859375
            ],
            "ypr": [
                0.0,
                0.0,
                -0.0
            ],
            "scale": 1.0,
            "enableCEPersistency": 0
        },
        {
            "name": "CarBattery",
            "pos": [
                4474.62109375,
                339.3605041503906,
                10076.01171875
            ],
            "ypr": [
                0.0,
                0.0,
                -0.0
            ],
            "scale": 1.0,
            "enableCEPersistency": 0
        },
        {
            "name": "CarBattery",
            "pos": [
                4474.138671875,
                339.4922180175781,
                10074.560546875
            ],
            "ypr": [
                0.0,
                0.0,
                -0.0
            ],
            "scale": 1.0,
            "enableCEPersistency": 0
        },
        {
            "name": "GlowPlug",
            "pos": [
                4474.65966796875,
                339.3411865234375,
                10074.10546875
            ],
            "ypr": [
                0.0,
                0.0,
                -0.0
            ],
            "scale": 1.0,
            "enableCEPersistency": 0
        },
        {
            "name": "GlowPlug",
            "pos": [
                4472.65869140625,
                339.7513122558594,
                10072.84375
            ],
            "ypr": [
                0.0,
                0.0,
                -0.0
            ],
            "scale": 1.0,
            "enableCEPersistency": 0
        },
        {
            "name": "bldr_prop_CanisterGasoline",
            "pos": [
                4475.3896484375,
                339.6294860839844,
                10075.0908203125
            ],
            "ypr": [
                0.0,
                0.0,
                -0.0
            ],
            "scale": 1.0,
            "enableCEPersistency": 0
        },
        {
            "name": "bldr_prop_CanisterGasoline",
            "pos": [
                4475.27880859375,
                339.17596435546877,
                10076.15234375
            ],
            "ypr": [
                0.0,
                0.0,
                -0.0
            ],
            "scale": 1.0,
            "enableCEPersistency": 0
        },
        {
            "name": "CanisterGasoline",
            "pos": [
                4474.9560546875,
                339.0565185546875,
                10077.662109375
            ],
            "ypr": [
                0.0,
                0.0,
                -0.0
            ],
            "scale": 1.0,
            "enableCEPersistency": 0
        },
        {
            "name": "CanisterGasoline",
            "pos": [
                4474.48095703125,
                339.02874755859377,
                10078.8056640625
            ],
            "ypr": [
                0.0,
                0.0,
                -0.0
            ],
            "scale": 1.0,
            "enableCEPersistency": 0
        },
        {
            "name": "SparkPlug",
            "pos": [
                4471.51171875,
                339.1159973144531,
                10074.7255859375
            ],
            "ypr": [
                0.0,
                0.0,
                -0.0
            ],
            "scale": 1.0,
            "enableCEPersistency": 0
        },
        {
            "name": "SparkPlug",
            "pos": [
                4472.42236328125,
                339.054931640625,
                10075.5107421875
            ],
            "ypr": [
                0.0,
                0.0,
                -0.0
            ],
            "scale": 1.0,
            "enableCEPersistency": 0
        },
        {
            "name": "Offroad_02_Wheel",
            "pos": [
                4475.25537109375,
                339.7460021972656,
                10067.9794921875
            ],
            "ypr": [
                0.0,
                0.0,
                -0.0
            ],
            "scale": 1.0,
            "enableCEPersistency": 0
        },
        {
            "name": "Offroad_02_Wheel",
            "pos": [
                4475.99462890625,
                339.525390625,
                10073.7392578125
            ],
            "ypr": [
                0.0,
                0.0,
                -0.0
            ],
            "scale": 1.0,
            "enableCEPersistency": 0
        },
        {
            "name": "Offroad_02_Wheel",
            "pos": [
                4468.64111328125,
                339.715087890625,
                10071.0791015625
            ],
            "ypr": [
                0.0,
                0.0,
                -0.0
            ],
            "scale": 1.0,
            "enableCEPersistency": 0
        },
        {
            "name": "Offroad_02_Wheel",
            "pos": [
                4472.015625,
                339.8191833496094,
                10067.0615234375
            ],
            "ypr": [
                0.0,
                0.0,
                -0.0
            ],
            "scale": 1.0,
            "enableCEPersistency": 0
        },
        {
            "name": "Offroad_02_Hood",
            "pos": [
                4479.20068359375,
                340.17572021484377,
                10070.7744140625
            ],
            "ypr": [
                0.0,
                0.0,
                -0.0
            ],
            "scale": 1.0,
            "enableCEPersistency": 0
        },
        {
            "name": "Offroad_02_Trunk_Rust",
            "pos": [
                4470.00390625,
                340.5430908203125,
                10068.0263671875
            ],
            "ypr": [
                0.0,
                0.0,
                -0.0
            ],
            "scale": 1.0,
            "enableCEPersistency": 0
        },
        {
            "name": "M4A1_Green",
            "pos": [
                4477.791015625,
                339.89141845703127,
                10073.662109375
            ],
            "ypr": [
                0.0,
                0.0,
                -0.0
            ],
            "scale": 1.0,
            "enableCEPersistency": 0
        },
        {
            "name": "M4_Suppressor",
            "pos": [
                4478.2783203125,
                339.9466247558594,
                10073.3798828125
            ],
            "ypr": [
                0.0,
                0.0,
                -0.0
            ],
            "scale": 1.0,
            "enableCEPersistency": 0
        },
        {
            "name": "M4_MPBttstck_Black",
            "pos": [
                4478.080078125,
                339.652587890625,
                10073.810546875
            ],
            "ypr": [
                0.0,
                0.0,
                -0.0
            ],
            "scale": 1.0,
            "enableCEPersistency": 0
        },
        {
            "name": "M4_PlasticHndgrd_Green",
            "pos": [
                4477.169921875,
                339.3398132324219,
                10074.4931640625
            ],
            "ypr": [
                0.0,
                0.0,
                -0.0
            ],
            "scale": 1.0,
            "enableCEPersistency": 0
        },
        {
            "name": "Mag_CMAG_40Rnd_Green",
            "pos": [
                4477.80029296875,
                339.4857482910156,
                10074.3232421875
            ],
            "ypr": [
                0.0,
                0.0,
                -0.0
            ],
            "scale": 1.0,
            "enableCEPersistency": 0
        },
        {
            "name": "Mag_CMAG_40Rnd_Black",
            "pos": [
                4478.35400390625,
                339.2251892089844,
                10073.71484375
            ],
            "ypr": [
                0.0,
                0.0,
                -0.0
            ],
            "scale": 1.0,
            "enableCEPersistency": 0
        }
    ]
}